curvtools/__init__.py
curvtools/_version.py
curvtools/constants.py
curvtools/version.py
curvtools/cli/__init__.py
curvtools/cli/cache_tool/README_CONFIGURABLE.md
curvtools/cli/cache_tool/__init__.py
curvtools/cli/cache_tool/addresses.py
curvtools/cli/cache_tool/cache.py
curvtools/cli/cache_tool/cache_config.py
curvtools/cli/cache_tool/cache_tool4.py
curvtools/cli/cache_tool/cache_type.py
curvtools/cli/cache_tool/cli.py
curvtools/cli/cache_tool/tag_ram_way_interleaver.py
curvtools/cli/curvcfg/__init__.py
curvtools/cli/curvcfg/__main__.py
curvtools/cli/curvcfg/board.py
curvtools/cli/curvcfg/cli.py
curvtools/cli/curvcfg/completions.py
curvtools/cli/curvcfg/generate.py
curvtools/cli/curvcfg/merge.py
curvtools/cli/curvcfg/pytest.ini
curvtools/cli/curvcfg/settings.py
curvtools/cli/curvcfg/show.py
curvtools/cli/curvcfg/version.py
curvtools/cli/curvcfg/cli_helpers/__init__.py
curvtools/cli/curvcfg/cli_helpers/default_map.py
curvtools/cli/curvcfg/cli_helpers/delayed_param/__init__.py
curvtools/cli/curvcfg/cli_helpers/delayed_param/resolveable.py
curvtools/cli/curvcfg/cli_helpers/delayed_param/resolveable_factory.py
curvtools/cli/curvcfg/cli_helpers/help_formatter/__init__.py
curvtools/cli/curvcfg/cli_helpers/help_formatter/epilog.py
curvtools/cli/curvcfg/cli_helpers/help_formatter/help_formatter.py
curvtools/cli/curvcfg/cli_helpers/opts/__init__.py
curvtools/cli/curvcfg/cli_helpers/opts/board_device_opts.py
curvtools/cli/curvcfg/cli_helpers/opts/build_dir_opts.py
curvtools/cli/curvcfg/cli_helpers/opts/curv_root_dir_opt.py
curvtools/cli/curvcfg/cli_helpers/opts/expand_special_vars.py
curvtools/cli/curvcfg/cli_helpers/opts/fs_path_opt.py
curvtools/cli/curvcfg/cli_helpers/opts/verbosity_opts.py
curvtools/cli/curvcfg/cli_helpers/opts/version_opt.py
curvtools/cli/curvcfg/cli_helpers/paramtypes/__init__.py
curvtools/cli/curvcfg/cli_helpers/paramtypes/board.py
curvtools/cli/curvcfg/cli_helpers/paramtypes/device.py
curvtools/cli/curvcfg/cli_helpers/paramtypes/merged_toml.py
curvtools-0.0.19.dist-info/METADATA
curvtools-0.0.19.dist-info/WHEEL
curvtools-0.0.19.dist-info/entry_points.txt
curvtools-0.0.19.dist-info/RECORD
