Metadata-Version: 2.4
Name: curvtools
Version: 0.0.19
Summary: CLI tools for the Curv RISC-V CPU project
Project-URL: homepage, https://github.com/curvcpu/curv-python/tree/main/packages/curvtools/readme.md
Project-URL: repository, https://github.com/curvcpu/curv-python
Project-URL: documentation, https://github.com/curvcpu/curv-python/tree/main/packages/curvtools/readme.md
Project-URL: issues, https://github.com/curvcpu/curv-python/issues
Author: Mike Goelzer
License: MIT
Classifier: Programming Language :: Python :: 3 :: Only
Requires-Python: >=3.10
Requires-Dist: click>=8.1.0
Requires-Dist: curv>=0
Requires-Dist: curvpyutils>=0
Requires-Dist: importlib-metadata>=6.0.0
Requires-Dist: jinja2>=3
Requires-Dist: platformdirs>=4
Requires-Dist: python-dotenv>=1.1.0
Requires-Dist: rich
Requires-Dist: shtab
Requires-Dist: tomli-w
Requires-Dist: tomli>=2; python_version < '3.11'
